{"uri": "http://raycomnbc.worldnow.com/story/31223354/5-shot-at-greene-co-nightclub", "title": "5 shot at Greene Co. nightclub", "dct": "Mon, 15 Feb 2016 15:59:00 GMT", "id": "f6c77e803c45913f8491750bc3b2029e", "content": "GREENE COUNTY, AL (WBRC) -\nGreene County Sheriff's deputies are asking for the public's help to solve a club shooting that injured five people this weekend.\nIt happened between 1 a.m. and 2 a.m. Sunday in the town of Union.\nThe club sits on Earnest Friday Road. Signs at the club say Dr. Rocks but people in the neighborhood around the building also refer to it as Howard's.\nAt least four of the victims have non-life threatening injuries according Lt. Jeremy Rancher with the Greene County Sheriff's Office. A fifth victim was take to UAB and his condition is unknown at this time.\nThe son of woman who lives near the club tells WBRC he now fears for her safety.\n\"A bullet could have so easily struck her. So I'm very much concerned about that. And I'm very much concerned about this kind of activity going on in the community,\" said John Burton.\nNo one has been charged in the shooting and investigators haven't released a motive in the case.\nLt. Rancher said they expect to make several arrests in the case over the next few days.\nCopyright 2016 WBRC.All rights reserved."}