{"uri": "http://www.idahopress.com/news/local/teen-killed-in-shooting-identified/article_5cbb1ab0-7818-11e5-ab71-23625c2d33e0.html", "title": "Teen killed in shooting identified", "dct": "Wed, 21 Oct 2015 00:00:00 GMT", "id": "44468c74d23405945036a08b5249f9d2", "content": "MERIDIAN \u2013 The 15-year-old boy who died after being shot in the head Saturday has been identified as Tristan Fenton, of Meridian, according to the Ada County Coroner's Office.\nAccording to police, David Provencio, 18, of Meridian, was handling one of two handguns in the room, when he pointed the gun, which he thought was unloaded, at the victim's head and pulled the trigger.\nProvencio was arrested on suspicion of involuntary manslaughter for the shooting that occurred in the 2300 block of East Franklin Road in Meridian. Police claim Provencio originally said the incident was a suicide."}