{"uri": "http://abc13.com/news/4-adults-found-dead-after-shooting-in-bastrop/1440264/", "title": "Shooting at Bastrop apartment complex leaves 4 dead", "dct": "Sat, 23 Jul 2016 00:00:00 GMT", "id": "7d1427b65d23c206da457a379042926b", "content": "BASTROP, TX (KTRK) --\nA shooting at a Texas apartment complex on Saturday left four people dead including the suspected shooter, police said.\nBastrop Police Det. Vicky Steffanic said at a news briefing that the dead were one man, two women and a child.\nAnother child was taken to a hospital with injuries that were not life threatening, she said.\n\"The shooter is among the dead and there is no further threat to the public,\" Steffanic said.\nThe identities of the dead are not being released pending notification of family.\nSteffanic declined to comment on a motive for the shooting.\nAt least one nearby resident told the Austin American-Statesman that those found dead were residents of the complex.\nPolice initially said there could be as many as five dead, but that was later revised to four when it was determined that the suspected shooter was among the fatalities.\nBastrop is a town of about 7,500 people located 35 miles southeast of Austin.\nThe Associated Press contributed to this report.\nTo get alerts for breaking news, download the abc13 news app for iPhone or Android. You can also get breaking news alerts sent to you by email."}