{"uri": "http://www.wmcactionnews5.com/story/32705255/4-year-old-grazed-in-shooting", "title": "4-year-old grazed in shooting", "dct": "Mon, 08 Aug 2016 12:05:00 GMT", "id": "e4a6bca6bba695a6119c462e8c377c99", "content": "MEMPHIS, TN (WMC) -\nA four year old was caught in the middle of gunfire.\nPolice said the child was grazed by a bullet Saturday on West Essex Avenue near Arkansas Street.\nThe child was taken to Le Bonheur, but is expected to be okay.\nIt\u2019s not clear who fired the gun at this time.\nCopyright 2016 WMC Action News 5. All rights reserved."}