{"uri": "http://wtvr.com/2016/11/06/grove-avenue-shooting-investigation/", "title": "Grove Avenue shooting under investigation", "dct": "Sun, 06 Nov 2016 19:31:00 GMT", "id": "f666ccaa3e86a2c458fcca90ce522bde", "content": "RICHMOND, Va. \u2014 Police are investigating an accidental shooting reported on Grove Avenue, near Woodlawn Avenue, in Richmond\u2019s West End.\nNeighbors along the 4300 block of Grove Avenue saw a truck pull into a parking lot, then heard a single gun shot.\nEMS arrives after neighbors called 911 and rushed the person in the truck to the hospital.\nThat person\u2019s condition has not yet been released.\nA Richmond Police spokesperson referred to the incident as an \u201caccidental shooting.\u201d\nThis is a developing story. Submit a news tip here."}