{"uri": "http://www.al.com/news/montgomery/index.ssf/2016/04/4_shot_at_house_party_in_south.html#incart_river_index", "title": "4 shot at house party in south Alabama", "dct": "Sat, 16 Apr 2016 08:36:00 GMT", "id": "fa2ab9460d1e31ce6bb4de8811370e04", "content": "Four people were shot and injured while attending a house party early Saturday morning in Enterprise, police say.\nEnterprise police said multiple shots were fired on Baxter Street at around 1:42 a.m. Officers arrived on the scene to find dozens of people standing in the street.\nThe shooting stemmed from a verbal and physical altercation, according to police.\nThe victims were transported to an unspecified hospital with non-life threatening injuries.\nThe shooting remains under investigation. Anyone with information is asked to call Enterprise Police Department at 334-347-2222."}