{"uri": "http://www.kmbc.com/news/boy-15-charged-with-murder-in-driveby-shooting-death/41566076", "title": "Boy, 15, charged with murder in drive-by shooting death", "dct": "Thu, 08 Sep 2016 00:45:00 GMT", "id": "4f81bc8f83a47f655ff5b89ace058357", "content": "KANSAS CITY, Kan. \u2014\nA 15-year-old boy has been charged with first-degree murder in Friday\u2019s drive-by shooting that killed Brannae' Browne.\nThe Wyandotte County district attorney announced the charges against Michael Adams Jr. Wednesday afternoon, hours before a planned vigil to honor Browne.\nBrowne was on the front porch outside a friend\u2019s home when someone fired shots from a passing car. She died of her wounds. A second person was also injured.\nPolice said Adams\u2019 mother, Natasha Hays, was killed in a drive-by shooting three days earlier at 2417 N. Ninth St.\nProsecutors also charged Adams with criminal discharge of a firearm at an occupied dwelling and criminal use of a weapon. Police said the criminal use of a weapon happened when Adams and police came into contact during the Hays investigation."}