{"uri": "http://www.accessnorthga.com/detail.php?n=286932", "title": "3-year-old killed in accidental shooting in Jefferson", "dct": "Sun, 29 Mar 2015 00:00:00 GMT", "id": "719523b448b1300af46aa3f715b8a2ff", "content": "JEFFERSON - A 3-year-old child has been killed in what appears to be an accidental shooting in Jefferson.\nJefferson Police Chief Joe Wirthman confirmed the shooting Sunday evening. He released no details, however, saying that the Georgia Bureau of Investigation is taking the lead in the investigation.\nWirthman said he expected more details to be released on Monday.\n\u00a9 Copyright 2017 AccessWDUN.com\nAll rights reserved. This material may not be published, broadcast, rewritten, or redistributed without permission."}