{"uri": "https://www.gofundme.com/medical-funds-for-colvin-broome", "title": "Medical Funds for Colvin Broome", "dct": "Wed, 07 Dec 2016 00:00:00 GMT", "id": "7c03cc5e5cd82ee8957be039448c5699", "content": "Colvin Broome 3 yrs old suffered a gunshot would to the head December 5, 2016. The toddler is in a medically induced coma at the Sanford's Children Hospital in Fargo, ND.\nWe are raising funds for Medical expenses, and emergency expenses for his parents to stay by his side\nin the Intensive Care Unit.\nAll donations and urgent prayers are greatly appreaciated at this time."}