{"uri": "http://www.wltx.com/news/local/deputies-toddler-killed-while-dad-was-working-with-gun/312957134", "title": "Deputies: Toddler Killed While Dad was Working with Gun", "dct": "Fri, 02 Sep 2016 00:00:00 GMT", "id": "62873c0aca2a51a3a1d531a31c5cca98", "content": "Richland County, SC (WLTX) - Richland County deputies have released more details of an accidental shooting that left a two-year-old girl dead and her father and sister injured.\nOfficers say around 6 p.m. Thursday, the father was with his two girls inside a unit at the Meredith Square Town Homes off Bookfield Road. Deputies say early evidence suggests the father was attempting to make the gun safe, and the weapon went off, striking him in the hand and both of his daughters in the upper body.\nHis two-year-old daughter, Heaven Miller, died from her injuries at the hospital. The four-year-old daughter suffered what are described as non life-threatening injuries.\nThe investigation into the death continues."}