{"uri": "http://www.orlandosentinel.com/news/breaking-news/os-two-teens-killed-pine-hills-shooting-20160617-story.html", "title": "Two teens killed in Pine Hills shooting, deputies say", "dct": "Fri, 17 Jun 2016 05:38:00 GMT", "id": "0946508a0e81264db83417360b760fb6", "content": "A 16-year-old boy and 18-year-old man were shot to death late Thursday night outside a Pine Hills home.\nDeputies responded just before 11 p.m. to the 2300 block of Fontainebleau Drive to reports of a shooting, according to the Orange County Sheriff's Office.\nThe teenagers, whose names haven't been released, were lying on the ground with gunshot wounds, deputies said.\nEmergency medical crews took both to a local hospital, where they died.\nDeputies said witnesses saw a dark-colored vehicle driving away from the scene right after the shooting.\nDetectives were called to the scene, in a neighborhood tucked between Princeton Street and Silver Star Road, about a mile east of Maynard Evans High School.\nNo other details about the incident have been released.\nDeputies haven't released any information about a possible suspect.\nsallen@orlandosentinel.com or 407-420-5417"}